printcraft/examples/auto_detect_example.py
printcraft/examples/json_example.py
printcraft/examples/table_example.py
printcraft/printcraft/__init__.py
printcraft/printcraft/core.py
printcraft/printcraft/dict_formatter.py
printcraft/printcraft/json_formatter.py
printcraft/printcraft/list_formatter.py
printcraft/printcraft/logging_formatter.py
printcraft/printcraft/preview.py
printcraft/printcraft/table_formatter.py
printcraft/printcraft/themes.py
printcraft/printcraft/utils.py
printcraft-1.0.2.dist-info/licenses/LICENSE
printcraft-1.0.2.dist-info/METADATA
printcraft-1.0.2.dist-info/WHEEL
printcraft-1.0.2.dist-info/top_level.txt
printcraft-1.0.2.dist-info/RECORD
