Metadata-Version: 2.4
Name: printcraft
Version: 1.0.2
Summary: A pretty-printing library for dicts, lists, tables, and JSON.
Author-email: Sayed Afaq Ahmed <sayedafaq.contact@gmail.com>
License-Expression: MIT
Requires-Python: >=3.8
License-File: LICENSE
Dynamic: license-file
